Add_Sub.v
module Add_sub (
    input [7:0] A,
    B,
    input sel,
    output [7:0] out,
    output cout
);
  wire [7:0] b;
  wire c;
  wire [3:0] x, y;
  assign b = B ^ {8{sel}};
  cla4 adder_sub1 (
      .a(A[3:0]),
      .b(b[3:0]),
      .carry(sel),
      .carry_out(c),
      .cla_out(x)
  );
  cla4 adder_sub2 (
      .a(A[7:4]),
      .b(b[7:4]),
      .carry(c),
      .carry_out(cout),
      .cla_out(y)
  );
  assign out = {y, x};
endmodule

module cla4 (
    input [3:0] a,
    b,
    input carry,
    output [3:0] cla_out,
    output carry_out
);
  wire [3:0] p, s, g;
  wire [4:0] c;

  assign p = a ^ b;
  assign g = a & b;
  assign c[0] = carry;
  assign c[1] = g[0] | (p[0] & c[0]);
  assign c[2] = g[1] | (p[1] & g[0]) | (p[1] & p[0] & c[0]);
  assign c[3] = g[2] | p[2] & g[1] | (p[2] & p[1] & g[0]) | (p[2] & p[1] & p[0] & c[0]);
  assign c[4] = g[3] | p[3] & g[2] | p[3] & p[2] & g[1] | (p[3] & p[2] & p[1] & g[0]) | (p[3] & p[2] & p[1] & p[0] & c[0]);
  assign carry_out = c[4];

  assign cla_out = p ^ c[3:0];
endmodule

ALU_main.v
module ALU_main (
    input clk,
    rst_n,
    valid,
    input [3:0] opcode,
    input [7:0] A,
    B,
    output reg [7:0] result,
    output reg done
);
  wire  [7:0] add_result,sub_result,and_result,or_result,xor_result,not_result,Shift_left_result,shift_right_result;
  wire ca, cb, equl_result;

  localparam ADD = 4'b0000;
  localparam SUB = 4'b0001;
  localparam AND = 4'b0010;
  localparam OR = 4'b0011;
  localparam Xor = 4'b0100;
  localparam Not = 4'b0101;
  localparam Shift_left = 4'b0110;
  localparam Shift_right = 4'b0111;
  localparam Equal = 4'b1000;

  Add_sub adsx (
      .A(A),
      .B(B),
      .sel(1'b0),
      .out(add_result),
      .cout(ca)
  );
  Add_sub subx (
      .A(A),
      .B(B),
      .sel(1'b1),
      .out(sub_result),
      .cout(cb)
  );
  assign and_result = A & B;
  assign or_result = A | B;
  assign xor_result = A ^ B;
  assign not_result = ~A;
  assign Shift_left_result = A << 1;
  assign shift_right_result = A >> 1;
  assign equl_result = A == B ? 8'b00000001 : 8'b00000000;
  always @(posedge clk or negedge rst_n) begin
    if (!rst_n) begin
      result <= 8'b0;
      done   <= 1'b0;
    end else if (valid) begin
      case (opcode)
        ADD: result <= add_result;
        SUB: result <= sub_result;
        AND: result <= and_result;
        OR: result <= or_result;
        Xor: result <= xor_result;
        Not: result <= not_result;
        Shift_left: result <= Shift_left_result;
        Shift_right: result <= shift_right_result;
        Equal: result <= equl_result;
        default: result <= 8'b0;
      endcase
      done <= 1;
    end else if (!valid) begin
      done <= 1'b0;
    end
  end
endmodule

ALU_TB.v
module ALU_TB;
  reg clktb, rst_ntb, validtb;
  reg [3:0] opcodetb;
  reg [7:0] atb, btb;
  wire [7:0] restb;
  wire donetb;

  ALU_main ALU (
      .clk(clktb),
      .rst_n(rst_ntb),
      .valid(validtb),
      .opcode(opcodetb),
      .A(atb),
      .B(btb),
      .result(restb),
      .done(donetb)
  );
  initial begin
    clktb = 1'b0;
  end
  always #5 clktb = ~clktb;
  initial begin
    rst_ntb  = 1'b1;
    validtb  = 1'b0;
    opcodetb = 4'b0000;
    atb      = 8'b0;
    btb      = 8'b0;
    $display("reset=%b,valid=%b,Opcode=%b A=%d B=%d Result=%d Done=%b", rst_ntb, validtb, opcodetb,
             atb, btb, restb, donetb);
    #2 rst_ntb = 1'b0;
    #2 rst_ntb = 1'b1;
    #2 validtb = 1'b1;
    #2 atb = 8'b00000101;
    #2 btb = 8'b00000101;
    opcodetb = 4'b0000;
    @(posedge clktb);
    #1
    $display(
        "reset=%b,valid=%b,Opcode=%b A=%d B=%d Result=%d Done=%b",
        rst_ntb,
        validtb,
        opcodetb,
        atb,
        btb,
        restb,
        donetb
    );
    opcodetb = 4'b0001;
    @(posedge clktb);
    #1
    $display(
        "reset=%b,valid=%b,Opcode=%b A=%d B=%d Result=%d Done=%b",
        rst_ntb,
        validtb,
        opcodetb,
        atb,
        btb,
        restb,
        donetb
    );
    opcodetb = 4'b0010;
    @(posedge clktb);
    #1
    $display(
        "reset=%b,valid=%b,Opcode=%b A=%d B=%d Result=%d Done=%b",
        rst_ntb,
        validtb,
        opcodetb,
        atb,
        btb,
        restb,
        donetb
    );
    opcodetb = 4'b0011;
    @(posedge clktb);
    #1
    $display(
        "reset=%b,valid=%b,Opcode=%b A=%d B=%d Result=%d Done=%b",
        rst_ntb,
        validtb,
        opcodetb,
        atb,
        btb,
        restb,
        donetb
    );
    opcodetb = 4'b0100;
    @(posedge clktb);
    #1
    $display(
        "reset=%b,valid=%b,Opcode=%b A=%d B=%d Result=%d Done=%b",
        rst_ntb,
        validtb,
        opcodetb,
        atb,
        btb,
        restb,
        donetb
    );
    opcodetb = 4'b0101;
    @(posedge clktb);
    #1
    $display(
        "reset=%b,valid=%b,Opcode=%b A=%d B=%d Result=%d Done=%b",
        rst_ntb,
        validtb,
        opcodetb,
        atb,
        btb,
        restb,
        donetb
    );
    opcodetb = 4'b0110;
    @(posedge clktb);
    #1
    $display(
        "reset=%b,valid=%b,Opcode=%b A=%d B=%d Result=%d Done=%b",
        rst_ntb,
        validtb,
        opcodetb,
        atb,
        btb,
        restb,
        donetb
    );
    opcodetb = 4'b0111;
    @(posedge clktb);
    #1
    $display(
        "reset=%b,valid=%b,Opcode=%b A=%d B=%d Result=%d Done=%b",
        rst_ntb,
        validtb,
        opcodetb,
        atb,
        btb,
        restb,
        donetb
    );
    opcodetb = 4'b1000;
    @(posedge clktb);
    #1
    $display(
        "reset=%b,valid=%b,Opcode=%b A=%d B=%d Result=%d Done=%b",
        rst_ntb,
        validtb,
        opcodetb,
        atb,
        btb,
        restb,
        donetb
    );
    #2 atb = 8'b01000001;
    #2 btb = 8'b00000101;
    opcodetb = 4'b0000;
    @(posedge clktb);
    #1
    $display(
        "reset=%b,valid=%b,Opcode=%b A=%d B=%d Result=%d Done=%b",
        rst_ntb,
        validtb,
        opcodetb,
        atb,
        btb,
        restb,
        donetb
    );
    opcodetb = 4'b0001;
    @(posedge clktb);
    #1
    $display(
        "reset=%b,valid=%b,Opcode=%b A=%d B=%d Result=%d Done=%b",
        rst_ntb,
        validtb,
        opcodetb,
        atb,
        btb,
        restb,
        donetb
    );
    opcodetb = 4'b0010;
    @(posedge clktb);
    #1
    $display(
        "reset=%b,valid=%b,Opcode=%b A=%d B=%d Result=%d Done=%b",
        rst_ntb,
        validtb,
        opcodetb,
        atb,
        btb,
        restb,
        donetb
    );
    opcodetb = 4'b0011;
    @(posedge clktb);
    #1
    $display(
        "reset=%b,valid=%b,Opcode=%b A=%d B=%d Result=%d Done=%b",
        rst_ntb,
        validtb,
        opcodetb,
        atb,
        btb,
        restb,
        donetb
    );
    opcodetb = 4'b0100;
    @(posedge clktb);
    #1
    $display(
        "reset=%b,valid=%b,Opcode=%b A=%d B=%d Result=%d Done=%b",
        rst_ntb,
        validtb,
        opcodetb,
        atb,
        btb,
        restb,
        donetb
    );
    opcodetb = 4'b0101;
    @(posedge clktb);
    #1
    $display(
        "reset=%b,valid=%b,Opcode=%b A=%d B=%d Result=%d Done=%b",
        rst_ntb,
        validtb,
        opcodetb,
        atb,
        btb,
        restb,
        donetb
    );
    opcodetb = 4'b0110;
    @(posedge clktb);
    #1
    $display(
        "reset=%b,valid=%b,Opcode=%b A=%d B=%d Result=%d Done=%b",
        rst_ntb,
        validtb,
        opcodetb,
        atb,
        btb,
        restb,
        donetb
    );
    opcodetb = 4'b0111;
    @(posedge clktb);
    #1
    $display(
        "reset=%b,valid=%b,Opcode=%b A=%d B=%d Result=%d Done=%b",
        rst_ntb,
        validtb,
        opcodetb,
        atb,
        btb,
        restb,
        donetb
    );
    opcodetb = 4'b1000;
    @(posedge clktb);
    #1
    $display(
        "reset=%b,valid=%b,Opcode=%b A=%d B=%d Result=%d Done=%b",
        rst_ntb,
        validtb,
        opcodetb,
        atb,
        btb,
        restb,
        donetb
    );
    #2 atb = 8'b01011101;
    #2 btb = 8'b01000001;
    opcodetb = 4'b0000;
    @(posedge clktb);
    #1
    $display(
        "reset=%b,valid=%b,Opcode=%b A=%d B=%d Result=%d Done=%b",
        rst_ntb,
        validtb,
        opcodetb,
        atb,
        btb,
        restb,
        donetb
    );
    opcodetb = 4'b0001;
    @(posedge clktb);
    #1
    $display(
        "reset=%b,valid=%b,Opcode=%b A=%d B=%d Result=%d Done=%b",
        rst_ntb,
        validtb,
        opcodetb,
        atb,
        btb,
        restb,
        donetb
    );
    opcodetb = 4'b0010;
    @(posedge clktb);
    #1
    $display(
        "reset=%b,valid=%b,Opcode=%b A=%d B=%d Result=%d Done=%b",
        rst_ntb,
        validtb,
        opcodetb,
        atb,
        btb,
        restb,
        donetb
    );
    opcodetb = 4'b0011;
    @(posedge clktb);
    #1
    $display(
        "reset=%b,valid=%b,Opcode=%b A=%d B=%d Result=%d Done=%b",
        rst_ntb,
        validtb,
        opcodetb,
        atb,
        btb,
        restb,
        donetb
    );
    opcodetb = 4'b0100;
    @(posedge clktb);
    #1
    $display(
        "reset=%b,valid=%b,Opcode=%b A=%d B=%d Result=%d Done=%b",
        rst_ntb,
        validtb,
        opcodetb,
        atb,
        btb,
        restb,
        donetb
    );
    opcodetb = 4'b0101;
    @(posedge clktb);
    #1
    $display(
        "reset=%b,valid=%b,Opcode=%b A=%d B=%d Result=%d Done=%b",
        rst_ntb,
        validtb,
        opcodetb,
        atb,
        btb,
        restb,
        donetb
    );
    opcodetb = 4'b0110;
    @(posedge clktb);
    #1
    $display(
        "reset=%b,valid=%b,Opcode=%b A=%d B=%d Result=%d Done=%b",
        rst_ntb,
        validtb,
        opcodetb,
        atb,
        btb,
        restb,
        donetb
    );
    opcodetb = 4'b0111;
    @(posedge clktb);
    #1
    $display(
        "reset=%b,valid=%b,Opcode=%b A=%d B=%d Result=%d Done=%b",
        rst_ntb,
        validtb,
        opcodetb,
        atb,
        btb,
        restb,
        donetb
    );
    opcodetb = 4'b1000;
    @(posedge clktb);
    #1
    $display(
        "reset=%b,valid=%b,Opcode=%b A=%d B=%d Result=%d Done=%b",
        rst_ntb,
        validtb,
        opcodetb,
        atb,
        btb,
        restb,
        donetb
    );
    #5 $finish;

  end
  initial begin
    $dumpfile("ADD_TB.vcd");
    $dumpvars(0, ALU_TB);
  end
endmodule

ADD_TB.vcd
$date
	Thu Sep 24 18:14:08 2026
$end
$version
	Icarus Verilog
$end
$timescale
	1s
$end
$scope module ALU_TB $end
$var wire 8 ! restb [7:0] $end
$var wire 1 " donetb $end
$var reg 8 # atb [7:0] $end
$var reg 8 $ btb [7:0] $end
$var reg 1 % clktb $end
$var reg 4 & opcodetb [3:0] $end
$var reg 1 ' rst_ntb $end
$var reg 1 ( validtb $end
$scope module ALU $end
$var wire 8 ) A [7:0] $end
$var wire 8 * B [7:0] $end
$var wire 8 + and_result [7:0] $end
$var wire 1 % clk $end
$var wire 8 , not_result [7:0] $end
$var wire 4 - opcode [3:0] $end
$var wire 8 . or_result [7:0] $end
$var wire 1 ' rst_n $end
$var wire 1 ( valid $end
$var wire 8 / xor_result [7:0] $end
$var wire 8 0 sub_result [7:0] $end
$var wire 8 1 shift_right_result [7:0] $end
$var wire 1 2 equl_result $end
$var wire 1 3 cb $end
$var wire 1 4 ca $end
$var wire 8 5 add_result [7:0] $end
$var wire 8 6 Shift_left_result [7:0] $end
$var parameter 4 7 ADD $end
$var parameter 4 8 AND $end
$var parameter 4 9 Equal $end
$var parameter 4 : Not $end
$var parameter 4 ; OR $end
$var parameter 4 < SUB $end
$var parameter 4 = Shift_left $end
$var parameter 4 > Shift_right $end
$var parameter 4 ? Xor $end
$var reg 1 " done $end
$var reg 8 @ result [7:0] $end
$scope module adsx $end
$var wire 8 A A [7:0] $end
$var wire 8 B B [7:0] $end
$var wire 8 C b [7:0] $end
$var wire 1 D sel $end
$var wire 4 E y [3:0] $end
$var wire 4 F x [3:0] $end
$var wire 8 G out [7:0] $end
$var wire 1 4 cout $end
$var wire 1 H c $end
$scope module adder_sub1 $end
$var wire 4 I a [3:0] $end
$var wire 4 J b [3:0] $end
$var wire 1 D carry $end
$var wire 4 K cla_out [3:0] $end
$var wire 4 L g [3:0] $end
$var wire 4 M p [3:0] $end
$var wire 1 H carry_out $end
$var wire 5 N c [4:0] $end
$upscope $end
$scope module adder_sub2 $end
$var wire 4 O a [3:0] $end
$var wire 4 P b [3:0] $end
$var wire 1 H carry $end
$var wire 4 Q cla_out [3:0] $end
$var wire 4 R g [3:0] $end
$var wire 4 S p [3:0] $end
$var wire 1 4 carry_out $end
$var wire 5 T c [4:0] $end
$upscope $end
$upscope $end
$scope module subx $end
$var wire 8 U A [7:0] $end
$var wire 8 V B [7:0] $end
$var wire 8 W b [7:0] $end
$var wire 1 X sel $end
$var wire 4 Y y [3:0] $end
$var wire 4 Z x [3:0] $end
$var wire 8 [ out [7:0] $end
$var wire 1 3 cout $end
$var wire 1 \ c $end
$scope module adder_sub1 $end
$var wire 4 ] a [3:0] $end
$var wire 4 ^ b [3:0] $end
$var wire 1 X carry $end
$var wire 4 _ cla_out [3:0] $end
$var wire 4 ` g [3:0] $end
$var wire 4 a p [3:0] $end
$var wire 1 \ carry_out $end
$var wire 5 b c [4:0] $end
$upscope $end
$scope module adder_sub2 $end
$var wire 4 c a [3:0] $end
$var wire 4 d b [3:0] $end
$var wire 1 \ carry $end
$var wire 4 e cla_out [3:0] $end
$var wire 4 f g [3:0] $end
$var wire 4 g p [3:0] $end
$var wire 1 3 carry_out $end
$var wire 5 h c [4:0] $end
$upscope $end
$upscope $end
$upscope $end
$upscope $end
$enddefinitions $end
$comment Show the parameter values. $end
$dumpall
b100 ?
b111 >
b110 =
b1 <
b11 ;
b101 :
b1000 9
b10 8
b0 7
$end
#0
$dumpvars
b11111 h
b1111 g
b0 f
b0 e
b1111 d
b0 c
b11111 b
b1111 a
b0 `
b0 _
b1111 ^
b0 ]
1\
b0 [
b0 Z
b0 Y
1X
b11111111 W
b0 V
b0 U
b0 T
b0 S
b0 R
b0 Q
b0 P
b0 O
b0 N
b0 M
b0 L
b0 K
b0 J
b0 I
0H
b0 G
b0 F
b0 E
0D
b0 C
b0 B
b0 A
bx @
b0 6
b0 5
04
13
12
b0 1
b0 0
b0 /
b0 .
b0 -
b11111111 ,
b0 +
b0 *
b0 )
0(
1'
b0 &
0%
b0 $
b0 #
x"
bx !
$end
#2
0"
b0 !
b0 @
0'
#4
1'
#5
1%
#6
1(
#8
b101 5
b101 G
b101 F
b101 K
b101 0
b101 [
b101 Z
b101 _
02
b101 M
b1010 a
b101 `
b101 .
b101 /
b11111010 ,
b1010 6
b10 1
b101 I
b101 ]
b101 #
b101 )
b101 A
b101 U
#10
b1010 N
b11111 b
b1010 5
b1010 G
b1010 F
b1010 K
b0 0
b0 [
b0 Z
b0 _
b0 M
b101 L
b1111 a
b0 `
12
b101 J
b1010 ^
b101 +
b0 /
b101 C
b11111010 W
b101 $
b101 *
b101 B
b101 V
0%
#15
1"
b1010 !
b1010 @
1%
#16
b1 &
b1 -
#20
0%
#25
b0 !
b0 @
1%
#26
b10 &
b10 -
#30
0%
#35
b101 !
b101 @
1%
#36
b11 &
b11 -
#40
0%
#45
1%
#46
b100 &
b100 -
#50
0%
#55
b0 !
b0 @
1%
#56
b101 &
b101 -
#60
0%
#65
b11111010 !
b11111010 @
1%
#66
b110 &
b110 -
#70
0%
#75
b1010 !
b1010 @
1%
#76
b111 &
b111 -
#80
0%
#85
b10 !
b10 @
1%
#86
b1000 &
b1000 -
#90
0%
#95
b1 !
b1 @
1%
#98
b11000 h
0\
b111 b
b10 N
b110 F
b110 K
b1000110 5
b1000110 G
b100 E
b100 Q
b1100 Z
b1100 _
b111100 0
b111100 [
b11 Y
b11 e
02
b100 M
b1 L
b100 S
b1011 a
b1011 g
b100 f
b1 +
b1000101 .
b1000100 /
b10111110 ,
b10000010 6
b100000 1
b1 I
b100 O
b1 ]
b100 c
b1000001 #
b1000001 )
b1000001 A
b1000001 U
#100
b0 &
b0 -
0%
#105
b1000110 !
b1000110 @
1%
#106
b1 &
b1 -
#110
0%
#115
b111100 !
b111100 @
1%
#116
b10 &
b10 -
#120
0%
#125
b1 !
b1 @
1%
#126
b11 &
b11 -
#130
0%
#135
b1000101 !
b1000101 @
1%
#136
b100 &
b100 -
#140
0%
#145
b1000100 !
b1000100 @
1%
#146
b101 &
b101 -
#150
0%
#155
b10111110 !
b10111110 @
1%
#156
b110 &
b110 -
#160
0%
#165
b10000010 !
b10000010 @
1%
#166
b111 &
b111 -
#170
0%
#175
b100000 !
b100000 @
1%
#176
b1000 &
b1000 -
#180
0%
#185
b0 !
b0 @
1%
#188
b11 T
1H
1\
b11111 b
b11010 N
b11111 h
b10 F
b10 K
b1100010 5
b1100010 G
b110 E
b110 Q
b1000 Z
b1000 _
b1011000 0
b1011000 [
b101 Y
b101 e
b1000 M
b101 L
b101 S
b111 a
b1000 `
b1010 g
b101 f
b101 +
b1011101 .
b1011000 /
b10100010 ,
b10111010 6
b101110 1
b1101 I
b101 O
b1101 ]
b101 c
b1011101 #
b1011101 )
b1011101 A
b1011101 U
#190
0H
b10 N
b1000 T
b11111 h
b1110 F
b1110 K
b10011110 5
b10011110 G
b1001 E
b1001 Q
b1100 Z
b1100 _
b11100 0
b11100 [
b1 Y
b1 e
b1100 M
b1 L
b1 S
b100 R
b11 a
b1100 `
b1110 g
b1 f
b1 J
b100 P
b1110 ^
b1011 d
b1000001 +
b11100 /
b1000001 C
b10111110 W
b0 &
b0 -
b1000001 $
b1000001 *
b1000001 B
b1000001 V
0%
#195
b10011110 !
b10011110 @
1%
#196
b1 &
b1 -
#200
0%
#205
b11100 !
b11100 @
1%
#206
b10 &
b10 -
#210
0%
#215
b1000001 !
b1000001 @
1%
#216
b11 &
b11 -
#220
0%
#225
b1011101 !
b1011101 @
1%
#226
b100 &
b100 -
#230
0%
#235
b11100 !
b11100 @
1%
#236
b101 &
b101 -
#240
0%
#245
b10100010 !
b10100010 @
1%
#246
b110 &
b110 -
#250
0%
#255
b10111010 !
b10111010 @
1%
#256
b111 &
b111 -
#260
0%
#265
b101110 !
b101110 @
1%
#266
b1000 &
b1000 -
#270
0%
#275
b0 !
b0 @
1%
